{
  "BreadCrum" : {
    "_id" : "wm-BreadCrum-wm.Variable-1482835307516",
    "name" : "BreadCrum",
    "owner" : "Page",
    "category" : "wm.Variable",
    "dataBinding" : [ ],
    "dataSet" : [ {
      "label" : "Home",
      "icon" : "glyphicon glyphicon-home",
      "link" : "#/Main"
    }, {
      "label" : "Open Forms",
      "icon" : "wi wi-ellipsis-v",
      "link" : "#/UserOpenForms"
    } ],
    "type" : "string",
    "isList" : true,
    "saveInPhonegap" : false
  },
  "FormsForUsersAndShared" : {
    "_id" : "wm-FormsForUsersAndShared-wm.ServiceVariable-1484734283571",
    "name" : "FormsForUsersAndShared",
    "owner" : "Page",
    "category" : "wm.ServiceVariable",
    "dataBinding" : [ {
      "target" : "closed",
      "value" : false,
      "type" : "boolean"
    }, {
      "target" : "creatorUser",
      "value" : "bind:Variables.CurrentUserDetails.dataSet.id",
      "type" : "integer"
    }, {
      "target" : "sharedWithUser",
      "value" : "bind:Variables.CurrentUserDetails.dataSet.id",
      "type" : "integer"
    } ],
    "type" : "cx2FormsForUsersAndSharedrtnType",
    "service" : "cx2",
    "operation" : "executeFormsForUsersAndShared",
    "operationId" : "QueryExecutionController_executeFormsForUsersAndShared",
    "operationType" : "get",
    "serviceType" : "DataService",
    "dataSet" : [ ],
    "isList" : true,
    "maxResults" : 20,
    "designMaxResults" : 10,
    "startUpdate" : false,
    "autoUpdate" : true,
    "inFlightBehavior" : "executeLast",
    "transformationRequired" : false,
    "saveInPhonegap" : false,
    "controller" : "QueryExecution",
    "spinnerContext" : "page"
  }
}