{
  "AdminsMunicipalities" : {
    "_id" : "wm-AdminsMunicipalities-wm.ServiceVariable-1478682649249",
    "name" : "AdminsMunicipalities",
    "owner" : "App",
    "category" : "wm.ServiceVariable",
    "dataBinding" : [ {
      "target" : "user",
      "value" : "bind:Variables.CurrentUserDetails.dataSet.id",
      "type" : "integer"
    } ],
    "type" : "com.civicxpress.cx2.models.query.AdminsMunicipalitiesResponse",
    "service" : "cx2",
    "operation" : "executeAdminsMunicipalities",
    "operationId" : "QueryExecutionController_executeAdminsMunicipalities",
    "operationType" : "get",
    "serviceType" : "DataService",
    "dataSet" : [ ],
    "isList" : true,
    "maxResults" : 20,
    "designMaxResults" : 10,
    "startUpdate" : false,
    "autoUpdate" : true,
    "inFlightBehavior" : "executeLast",
    "transformationRequired" : false,
    "saveInPhonegap" : false,
    "controller" : "QueryExecution"
  },
  "AdminVendorsList" : {
    "_id" : "wm-AdminVendorsList-wm.ServiceVariable-1480921073966",
    "name" : "AdminVendorsList",
    "owner" : "App",
    "category" : "wm.ServiceVariable",
    "dataBinding" : [ {
      "target" : "user",
      "value" : "bind:Variables.CurrentUserDetails.dataSet.id",
      "type" : "integer"
    } ],
    "type" : "com.civicxpress.cx2.models.query.AdminVendorsListResponse",
    "service" : "cx2",
    "operation" : "executeAdminVendorsList",
    "operationId" : "QueryExecutionController_executeAdminVendorsList",
    "operationType" : "get",
    "serviceType" : "DataService",
    "dataSet" : [ ],
    "isList" : true,
    "maxResults" : 20,
    "designMaxResults" : 10,
    "onSuccess" : "AdminVendorsListonSuccess($event, $scope)",
    "startUpdate" : false,
    "autoUpdate" : true,
    "inFlightBehavior" : "executeLast",
    "transformationRequired" : false,
    "saveInPhonegap" : false,
    "controller" : "QueryExecution",
    "spinnerContext" : "page"
  },
  "appNotification" : {
    "_id" : "wm-appErrorHandler-wm.NotificationVariable-1454664620943",
    "name" : "appNotification",
    "owner" : "App",
    "category" : "wm.NotificationVariable",
    "dataBinding" : [ {
      "target" : "class",
      "value" : "Error",
      "type" : "list"
    }, {
      "target" : "toasterPosition",
      "value" : "bottom right",
      "type" : "list"
    } ],
    "operation" : "toast"
  },
  "CompanyOpenFormsCount" : {
    "_id" : "wm-CompanyOpenFormsCount-wm.Variable-1486467750119",
    "name" : "CompanyOpenFormsCount",
    "owner" : "App",
    "category" : "wm.Variable",
    "dataBinding" : [ ],
    "dataSet" : {
      "dataValue" : ""
    },
    "type" : "string",
    "isList" : false,
    "saveInPhonegap" : false
  },
  "CurrentUserDetails" : {
    "_id" : "wm-CurrentUserDetails-wm.ServiceVariable-1478579290060",
    "name" : "CurrentUserDetails",
    "owner" : "App",
    "category" : "wm.ServiceVariable",
    "dataBinding" : [ {
      "target" : "id",
      "value" : "bind:Variables.loggedInUser.dataSet.id | stringToNumber",
      "type" : "integer"
    } ],
    "type" : "com.civicxpress.cx2.Users",
    "service" : "cx2",
    "operation" : "getUsers",
    "operationId" : "UsersController_getUsers",
    "operationType" : "get",
    "serviceType" : "DataService",
    "dataSet" : [ ],
    "isList" : false,
    "maxResults" : 20,
    "designMaxResults" : 10,
    "startUpdate" : false,
    "autoUpdate" : true,
    "inFlightBehavior" : "executeLast",
    "transformationRequired" : false,
    "saveInPhonegap" : false,
    "controller" : "Users"
  },
  "EmployeesMunicipalities" : {
    "_id" : "wm-EmployeesMunicipalities-wm.ServiceVariable-1478840896695",
    "name" : "EmployeesMunicipalities",
    "owner" : "App",
    "category" : "wm.ServiceVariable",
    "dataBinding" : [ {
      "target" : "user",
      "value" : "bind:Variables.CurrentUserDetails.dataSet.id",
      "type" : "integer"
    } ],
    "type" : "com.civicxpress.cx2.models.query.EmployeesMunicipalitiesResponse",
    "service" : "cx2",
    "operation" : "executeEmployeesMunicipalities",
    "operationId" : "QueryExecutionController_executeEmployeesMunicipalities",
    "operationType" : "get",
    "serviceType" : "DataService",
    "dataSet" : [ ],
    "isList" : true,
    "maxResults" : 20,
    "designMaxResults" : 10,
    "startUpdate" : false,
    "autoUpdate" : true,
    "inFlightBehavior" : "executeLast",
    "transformationRequired" : false,
    "saveInPhonegap" : false,
    "controller" : "QueryExecution"
  },
  "FileServiceUploadFile" : {
    "_id" : "wm-FileServiceUploadFile-wm.ServiceVariable-1482387425645",
    "name" : "FileServiceUploadFile",
    "owner" : "App",
    "category" : "wm.ServiceVariable",
    "dataBinding" : [ ],
    "type" : "com.civicxpress.fileservice.FileService.FileUploadResponse",
    "service" : "FileService",
    "operation" : "uploadFile",
    "operationId" : "FileController_uploadFile",
    "serviceType" : "JavaService",
    "dataSet" : [ ],
    "isList" : false,
    "maxResults" : 20,
    "designMaxResults" : 10,
    "startUpdate" : false,
    "autoUpdate" : true,
    "inFlightBehavior" : "executeLast",
    "transformationRequired" : false,
    "saveInPhonegap" : false,
    "isDefault" : true,
    "controller" : "File"
  },
  "FormDesignsForMuniAdmin" : {
    "_id" : "wm-FormDesignsForMuniAdmin-wm.Variable-1486467173350",
    "name" : "FormDesignsForMuniAdmin",
    "owner" : "App",
    "category" : "wm.Variable",
    "dataBinding" : [ ],
    "dataSet" : {
      "dataValue" : ""
    },
    "type" : "string",
    "isList" : false,
    "saveInPhonegap" : false
  },
  "goToPage_ClosedCases" : {
    "_id" : "wm-goToPage_ClosedCases-wm.NavigationVariable-1491395556167",
    "name" : "goToPage_ClosedCases",
    "owner" : "App",
    "category" : "wm.NavigationVariable",
    "dataBinding" : [ ],
    "operation" : "gotoPage",
    "pageName" : "ClosedCases",
    "dataSet" : [ ],
    "pageTransitions" : "none"
  },
  "goToPage_CodeEnforcementDashboard" : {
    "_id" : "wm-goToPage_CodeEnforcementDashboard-wm.NavigationVariable-1489466664404",
    "name" : "goToPage_CodeEnforcementDashboard",
    "owner" : "App",
    "category" : "wm.NavigationVariable",
    "dataBinding" : [ ],
    "operation" : "gotoPage",
    "pageName" : "CodeEnforcementDashboard",
    "dataSet" : [ ],
    "pageTransitions" : "none"
  },
  "goToPage_CompanyForms" : {
    "_id" : "wm-goToPage_CompanyForms-wm.NavigationVariable-1480417618463",
    "name" : "goToPage_CompanyForms",
    "owner" : "App",
    "category" : "wm.NavigationVariable",
    "dataBinding" : [ {
      "target" : "pageName",
      "value" : "CompanyForms",
      "type" : "string"
    } ],
    "operation" : "gotoPage",
    "pageName" : "CompanyForms",
    "dataSet" : [ {
      "type" : "integer",
      "target" : "companyId",
      "value" : "bind:Widgets.panelSelectCompany.Widgets.selectCompany.datavalue.ID"
    } ],
    "pageTransitions" : "none"
  },
  "goToPage_CompanyMunicipalities" : {
    "_id" : "wm-goToPage_CompanyMunicipalities-wm.NavigationVariable-1480417535902",
    "name" : "goToPage_CompanyMunicipalities",
    "owner" : "App",
    "category" : "wm.NavigationVariable",
    "dataBinding" : [ {
      "target" : "pageName",
      "value" : "CompanyMunicipalities",
      "type" : "string"
    } ],
    "operation" : "gotoPage",
    "pageName" : "CompanyMunicipalities",
    "dataSet" : [ {
      "type" : "integer",
      "target" : "companyId",
      "value" : "bind:Widgets.panelSelectCompany.Widgets.selectCompany.datavalue.ID"
    } ],
    "pageTransitions" : "none"
  },
  "goToPage_CompanyProfile" : {
    "_id" : "wm-goToPage_CompanyProfile-wm.NavigationVariable-1480417810969",
    "name" : "goToPage_CompanyProfile",
    "owner" : "App",
    "category" : "wm.NavigationVariable",
    "dataBinding" : [ {
      "target" : "pageName",
      "value" : "CompanyProfile",
      "type" : "string"
    } ],
    "operation" : "gotoPage",
    "pageName" : "CompanyProfile",
    "dataSet" : [ {
      "type" : "integer",
      "target" : "companyID",
      "value" : "bind:Widgets.panelSelectCompany.Widgets.selectCompany.datavalue.ID | stringToNumber"
    } ],
    "pageTransitions" : "none"
  },
  "goToPage_CompanyUsers" : {
    "_id" : "wm-goToPage_CompanyUsers-wm.NavigationVariable-1480417475427",
    "name" : "goToPage_CompanyUsers",
    "owner" : "App",
    "category" : "wm.NavigationVariable",
    "dataBinding" : [ {
      "target" : "pageName",
      "value" : "CompanyUsers",
      "type" : "string"
    } ],
    "operation" : "gotoPage",
    "pageName" : "CompanyUsers",
    "dataSet" : [ {
      "type" : "integer",
      "target" : "companyId",
      "value" : "bind:Widgets.panelSelectCompany.Widgets.selectCompany.datavalue.ID"
    } ],
    "pageTransitions" : "none"
  },
  "goToPage_CXAdmin" : {
    "_id" : "wm-goToPage_CXAdmin-wm.NavigationVariable-1478577233423",
    "name" : "goToPage_CXAdmin",
    "owner" : "App",
    "category" : "wm.NavigationVariable",
    "dataBinding" : [ ],
    "operation" : "gotoPage",
    "pageName" : "CXAdmin",
    "dataSet" : [ ],
    "pageTransitions" : "none"
  },
  "goToPage_CXCodeList" : {
    "_id" : "wm-goToPage_CXCodeList-wm.NavigationVariable-1491300073169",
    "name" : "goToPage_CXCodeList",
    "owner" : "App",
    "category" : "wm.NavigationVariable",
    "dataBinding" : [ {
      "target" : "pageName",
      "value" : "CXCodeList",
      "type" : "string"
    } ],
    "operation" : "gotoPage",
    "pageName" : "CXCodeList",
    "dataSet" : [ {
      "type" : "integer",
      "target" : "CodeSetId",
      "value" : "bind:Widgets.gridCodeSets.selecteditem.codeSetId"
    } ],
    "pageTransitions" : "none"
  },
  "goToPage_CXCodeSets" : {
    "_id" : "wm-goToPage_CXCodeSets-wm.NavigationVariable-1491299254750",
    "name" : "goToPage_CXCodeSets",
    "owner" : "App",
    "category" : "wm.NavigationVariable",
    "dataBinding" : [ ],
    "operation" : "gotoPage",
    "pageName" : "CXCodeSets",
    "dataSet" : [ ],
    "pageTransitions" : "none"
  },
  "goToPage_CXGlobalSettings" : {
    "_id" : "wm-goToPage_CXGlobalSettings-wm.NavigationVariable-1481624413329",
    "name" : "goToPage_CXGlobalSettings",
    "owner" : "App",
    "category" : "wm.NavigationVariable",
    "dataBinding" : [ ],
    "operation" : "gotoPage",
    "pageName" : "CXGlobalSettings",
    "dataSet" : [ ],
    "pageTransitions" : "none"
  },
  "goToPage_DashBoards" : {
    "_id" : "wm-goToPage_DashBoards-wm.NavigationVariable-1489142536978",
    "name" : "goToPage_DashBoards",
    "owner" : "App",
    "category" : "wm.NavigationVariable",
    "dataBinding" : [ ],
    "operation" : "gotoPage",
    "pageName" : "DashBoards",
    "dataSet" : [ ],
    "pageTransitions" : "none"
  },
  "goToPage_DataEntry" : {
    "_id" : "wm-goToPage_DataEntry-wm.NavigationVariable-1478537977414",
    "name" : "goToPage_DataEntry",
    "owner" : "App",
    "category" : "wm.NavigationVariable",
    "dataBinding" : [ ],
    "operation" : "gotoPage",
    "pageName" : "DataEntry",
    "dataSet" : [ ],
    "pageTransitions" : "none"
  },
  "goToPage_DevFormDataEntry" : {
    "_id" : "wm-goToPage_DevFormDataEntry-wm.NavigationVariable-1481543913034",
    "name" : "goToPage_DevFormDataEntry",
    "owner" : "App",
    "category" : "wm.NavigationVariable",
    "dataBinding" : [ ],
    "operation" : "gotoPage",
    "pageName" : "DevFormDataEntry",
    "dataSet" : [ ],
    "pageTransitions" : "none"
  },
  "goToPage_EditCase" : {
    "_id" : "wm-goToPage_EditCase-wm.NavigationVariable-1489476287938",
    "name" : "goToPage_EditCase",
    "owner" : "App",
    "category" : "wm.NavigationVariable",
    "dataBinding" : [ {
      "target" : "pageName",
      "value" : "EditCase",
      "type" : "string"
    } ],
    "operation" : "gotoPage",
    "pageName" : "EditCase",
    "dataSet" : [ {
      "type" : "integer",
      "target" : "CaseTypeId",
      "value" : "bind:Widgets.gridCasetypes.selecteditem.id"
    } ],
    "pageTransitions" : "none"
  },
  "goToPage_EditForm" : {
    "_id" : "wm-goToPage_EditForm-wm.NavigationVariable-1480049657857",
    "name" : "goToPage_EditForm",
    "owner" : "App",
    "category" : "wm.NavigationVariable",
    "dataBinding" : [ {
      "target" : "pageName",
      "value" : "EditForm",
      "type" : "list"
    } ],
    "operation" : "gotoPage",
    "pageName" : "EditForm",
    "dataSet" : [ {
      "type" : "integer",
      "target" : "FormTypeId",
      "value" : "bind:Widgets.gridFormTypes.selecteditem.ID | toNumber"
    } ],
    "pageTransitions" : "none"
  },
  "goToPage_EditGISRecord" : {
    "_id" : "wm-goToPage_EditGISRecord-wm.NavigationVariable-1482818287961",
    "name" : "goToPage_EditGISRecord",
    "owner" : "App",
    "category" : "wm.NavigationVariable",
    "dataBinding" : [ {
      "target" : "pageName",
      "value" : "EditGISRecord",
      "type" : "string"
    } ],
    "operation" : "gotoPage",
    "pageName" : "EditGISRecord",
    "dataSet" : [ {
      "type" : "integer",
      "target" : "GISRecordId",
      "value" : "bind:Widgets.grid3.selecteditem.id"
    } ],
    "pageTransitions" : "none"
  },
  "goToPage_EditInspection" : {
    "_id" : "wm-goToPage_EditInspection-wm.NavigationVariable-1488447542836",
    "name" : "goToPage_EditInspection",
    "owner" : "App",
    "category" : "wm.NavigationVariable",
    "dataBinding" : [ {
      "target" : "pageName",
      "value" : "EditInspection",
      "type" : "string"
    } ],
    "operation" : "gotoPage",
    "pageName" : "EditInspection",
    "dataSet" : [ {
      "type" : "integer",
      "target" : "InspectionDesignId",
      "value" : "bind:Widgets.gridInspectiondesign.selecteditem.id"
    } ],
    "pageTransitions" : "none"
  },
  "goToPage_FindForm" : {
    "_id" : "wm-goToPage_FindForm-wm.NavigationVariable-1486128615190",
    "name" : "goToPage_FindForm",
    "owner" : "App",
    "category" : "wm.NavigationVariable",
    "dataBinding" : [ ],
    "operation" : "gotoPage",
    "pageName" : "FindForm",
    "dataSet" : [ ],
    "pageTransitions" : "none"
  },
  "goToPage_ForgotPassword" : {
    "_id" : "wm-goToPage_ForgotPassword-wm.NavigationVariable-1479880545540",
    "name" : "goToPage_ForgotPassword",
    "owner" : "App",
    "category" : "wm.NavigationVariable",
    "dataBinding" : [ ],
    "operation" : "gotoPage",
    "pageName" : "ForgotPassword",
    "dataSet" : [ ],
    "pageTransitions" : "none"
  },
  "goToPage_Forms" : {
    "_id" : "wm-goToPage_Forms-wm.NavigationVariable-1484041515435",
    "name" : "goToPage_Forms",
    "owner" : "App",
    "category" : "wm.NavigationVariable",
    "dataBinding" : [ {
      "target" : "pageName",
      "value" : "Forms",
      "type" : "string"
    } ],
    "operation" : "gotoPage",
    "pageName" : "Forms",
    "dataSet" : [ {
      "type" : "string",
      "target" : "FormGUID",
      "value" : "bind:Widgets.gridOpenForms.selecteditem.formGuid"
    } ],
    "pageTransitions" : "none"
  },
  "goToPage_InspectionsDevDataEntry" : {
    "_id" : "wm-goToPage_InspectionsDevDataEntry-wm.NavigationVariable-1488866783864",
    "name" : "goToPage_InspectionsDevDataEntry",
    "owner" : "App",
    "category" : "wm.NavigationVariable",
    "dataBinding" : [ ],
    "operation" : "gotoPage",
    "pageName" : "InspectionsDevDataEntry",
    "dataSet" : [ ],
    "pageTransitions" : "none"
  },
  "goToPage_Main" : {
    "_id" : "wm-wm.NavigationVariable1389180517517",
    "name" : "goToPage_Main",
    "owner" : "App",
    "category" : "wm.NavigationVariable",
    "operation" : "gotoPage",
    "pageName" : "Main"
  },
  "goToPage_ManageCases" : {
    "_id" : "wm-goToPage_ManageCases-wm.NavigationVariable-1489471343380",
    "name" : "goToPage_ManageCases",
    "owner" : "App",
    "category" : "wm.NavigationVariable",
    "dataBinding" : [ ],
    "operation" : "gotoPage",
    "pageName" : "ManageCases",
    "dataSet" : [ ],
    "pageTransitions" : "none"
  },
  "goToPage_ManageCompanies" : {
    "_id" : "wm-goToPage_ManageCompanies-wm.NavigationVariable-1484344579277",
    "name" : "goToPage_ManageCompanies",
    "owner" : "App",
    "category" : "wm.NavigationVariable",
    "dataBinding" : [ ],
    "operation" : "gotoPage",
    "pageName" : "ManageCompanies",
    "dataSet" : [ ],
    "pageTransitions" : "none"
  },
  "goToPage_ManageForms" : {
    "_id" : "wm-goToPage_ManageForms-wm.NavigationVariable-1479980516604",
    "name" : "goToPage_ManageForms",
    "owner" : "App",
    "category" : "wm.NavigationVariable",
    "dataBinding" : [ ],
    "operation" : "gotoPage",
    "pageName" : "ManageForms",
    "dataSet" : [ ],
    "pageTransitions" : "none"
  },
  "goToPage_ManageGISData" : {
    "_id" : "wm-goToPage_ManageGISData-wm.NavigationVariable-1478683823337",
    "name" : "goToPage_ManageGISData",
    "owner" : "App",
    "category" : "wm.NavigationVariable",
    "dataBinding" : [ ],
    "operation" : "gotoPage",
    "pageName" : "ManageGISData",
    "dataSet" : [ ],
    "pageTransitions" : "none"
  },
  "goToPage_ManageInspections" : {
    "_id" : "wm-goToPage_ManageInspections-wm.NavigationVariable-1488261921592",
    "name" : "goToPage_ManageInspections",
    "owner" : "App",
    "category" : "wm.NavigationVariable",
    "dataBinding" : [ ],
    "operation" : "gotoPage",
    "pageName" : "ManageInspections",
    "dataSet" : [ ],
    "pageTransitions" : "none"
  },
  "goToPage_ManageMunicipalities" : {
    "_id" : "wm-goToPage_ManageMunicipalities-wm.NavigationVariable-1478585524041",
    "name" : "goToPage_ManageMunicipalities",
    "owner" : "App",
    "category" : "wm.NavigationVariable",
    "dataBinding" : [ ],
    "operation" : "gotoPage",
    "pageName" : "ManageMunicipalities",
    "dataSet" : [ ],
    "pageTransitions" : "none"
  },
  "goToPage_ManageMunicipalityVendors" : {
    "_id" : "wm-goToPage_ManageMunicipalityVendors-wm.NavigationVariable-1480585076347",
    "name" : "goToPage_ManageMunicipalityVendors",
    "owner" : "App",
    "category" : "wm.NavigationVariable",
    "dataBinding" : [ ],
    "operation" : "gotoPage",
    "pageName" : "ManageMunicipalityVendors",
    "dataSet" : [ ],
    "pageTransitions" : "none"
  },
  "goToPage_ManageProjects" : {
    "_id" : "wm-goToPage_ManageProjects-wm.NavigationVariable-1488559177055",
    "name" : "goToPage_ManageProjects",
    "owner" : "App",
    "category" : "wm.NavigationVariable",
    "dataBinding" : [ ],
    "operation" : "gotoPage",
    "pageName" : "ManageProjects",
    "dataSet" : [ ],
    "pageTransitions" : "none"
  },
  "goToPage_ManageRoles" : {
    "_id" : "wm-goToPage_ManageRoles-wm.NavigationVariable-1484344556601",
    "name" : "goToPage_ManageRoles",
    "owner" : "App",
    "category" : "wm.NavigationVariable",
    "dataBinding" : [ ],
    "operation" : "gotoPage",
    "pageName" : "ManageRoles",
    "dataSet" : [ ],
    "pageTransitions" : "none"
  },
  "goToPage_ManageSubscriptions" : {
    "_id" : "wm-goToPage_ManageSubscriptions-wm.NavigationVariable-1478603979180",
    "name" : "goToPage_ManageSubscriptions",
    "owner" : "App",
    "category" : "wm.NavigationVariable",
    "dataBinding" : [ ],
    "operation" : "gotoPage",
    "pageName" : "ManageSubscriptions",
    "dataSet" : [ ],
    "pageTransitions" : "none"
  },
  "goToPage_ManageUsers" : {
    "_id" : "wm-goToPage_ManageUsers-wm.NavigationVariable-1478585569002",
    "name" : "goToPage_ManageUsers",
    "owner" : "App",
    "category" : "wm.NavigationVariable",
    "dataBinding" : [ ],
    "operation" : "gotoPage",
    "pageName" : "ManageUsers",
    "dataSet" : [ ],
    "pageTransitions" : "none"
  },
  "goToPage_ManualFeeTypes" : {
    "_id" : "wm-goToPage_ManualFeeTypes-wm.NavigationVariable-1479722237149",
    "name" : "goToPage_ManualFeeTypes",
    "owner" : "App",
    "category" : "wm.NavigationVariable",
    "dataBinding" : [ ],
    "operation" : "gotoPage",
    "pageName" : "ManualFeeTypes",
    "dataSet" : [ ],
    "pageTransitions" : "none"
  },
  "goToPage_MunicipalityAdministration" : {
    "_id" : "wm-goToPage_MunicipalityAdministration-wm.NavigationVariable-1478577191075",
    "name" : "goToPage_MunicipalityAdministration",
    "owner" : "App",
    "category" : "wm.NavigationVariable",
    "dataBinding" : [ ],
    "operation" : "gotoPage",
    "pageName" : "MunicipalityAdministration",
    "dataSet" : [ ],
    "pageTransitions" : "none"
  },
  "goToPage_MunicipalityCodeList" : {
    "_id" : "wm-goToPage_MunicipalityCodeList-wm.NavigationVariable-1491306546863",
    "name" : "goToPage_MunicipalityCodeList",
    "owner" : "App",
    "category" : "wm.NavigationVariable",
    "dataBinding" : [ {
      "target" : "pageName",
      "value" : "MunicipalityCodeList",
      "type" : "string"
    } ],
    "operation" : "gotoPage",
    "pageName" : "MunicipalityCodeList",
    "dataSet" : [ {
      "type" : "integer",
      "target" : "CodeSetId",
      "value" : "bind:Widgets.gridCodeSets.selecteditem.codeSetId"
    } ],
    "pageTransitions" : "none"
  },
  "goToPage_MunicipalityCodeSets" : {
    "_id" : "wm-goToPage_MunicipalityCodeSets-wm.NavigationVariable-1491305595721",
    "name" : "goToPage_MunicipalityCodeSets",
    "owner" : "App",
    "category" : "wm.NavigationVariable",
    "dataBinding" : [ ],
    "operation" : "gotoPage",
    "pageName" : "MunicipalityCodeSets",
    "dataSet" : [ ],
    "pageTransitions" : "none"
  },
  "goToPage_MunicipalityInspections" : {
    "_id" : "wm-goToPage_MunicipalityInspections-wm.NavigationVariable-1488260207805",
    "name" : "goToPage_MunicipalityInspections",
    "owner" : "App",
    "category" : "wm.NavigationVariable",
    "dataBinding" : [ ],
    "operation" : "gotoPage",
    "pageName" : "MunicipalityInspections",
    "dataSet" : [ ],
    "pageTransitions" : "none"
  },
  "goToPage_MunicipalityProjects" : {
    "_id" : "wm-goToPage_MunicipalityProjects-wm.NavigationVariable-1487582313953",
    "name" : "goToPage_MunicipalityProjects",
    "owner" : "App",
    "category" : "wm.NavigationVariable",
    "dataBinding" : [ ],
    "operation" : "gotoPage",
    "pageName" : "MunicipalityProjects",
    "dataSet" : [ ],
    "pageTransitions" : "none"
  },
  "goToPage_MunicipalitySettings" : {
    "_id" : "wm-goToPage_MunicipalitySettings-wm.NavigationVariable-1479365831697",
    "name" : "goToPage_MunicipalitySettings",
    "owner" : "App",
    "category" : "wm.NavigationVariable",
    "dataBinding" : [ ],
    "operation" : "gotoPage",
    "pageName" : "MunicipalitySettings",
    "dataSet" : [ ],
    "pageTransitions" : "none"
  },
  "goToPage_MunicipalityUsers" : {
    "_id" : "wm-goToPage_MunicipalityUsers-wm.NavigationVariable-1478761593507",
    "name" : "goToPage_MunicipalityUsers",
    "owner" : "App",
    "category" : "wm.NavigationVariable",
    "dataBinding" : [ ],
    "operation" : "gotoPage",
    "pageName" : "MunicipalityUsers",
    "dataSet" : [ ],
    "pageTransitions" : "none"
  },
  "goToPage_MyCart" : {
    "_id" : "wm-goToPage_MyCart-wm.NavigationVariable-1478577283252",
    "name" : "goToPage_MyCart",
    "owner" : "App",
    "category" : "wm.NavigationVariable",
    "dataBinding" : [ ],
    "operation" : "gotoPage",
    "pageName" : "MyCart",
    "dataSet" : [ ],
    "pageTransitions" : "none"
  },
  "goToPage_MyCompany" : {
    "_id" : "wm-goToPage_MyCompany-wm.NavigationVariable-1480408882347",
    "name" : "goToPage_MyCompany",
    "owner" : "App",
    "category" : "wm.NavigationVariable",
    "dataBinding" : [ ],
    "operation" : "gotoPage",
    "pageName" : "MyCompany",
    "dataSet" : [ ],
    "pageTransitions" : "none"
  },
  "goToPage_MyFees" : {
    "_id" : "wm-goToPage_MyFees-wm.NavigationVariable-1490104122146",
    "name" : "goToPage_MyFees",
    "owner" : "App",
    "category" : "wm.NavigationVariable",
    "dataBinding" : [ ],
    "operation" : "gotoPage",
    "pageName" : "MyFees",
    "dataSet" : [ ],
    "pageTransitions" : "none"
  },
  "goToPage_MyMessages" : {
    "_id" : "wm-goToPage_MyMessages-wm.NavigationVariable-1490120425160",
    "name" : "goToPage_MyMessages",
    "owner" : "App",
    "category" : "wm.NavigationVariable",
    "dataBinding" : [ ],
    "operation" : "gotoPage",
    "pageName" : "MyMessages",
    "dataSet" : [ ],
    "pageTransitions" : "none"
  },
  "goToPage_MyMunicipality" : {
    "_id" : "wm-goToPage_MyMunicipality-wm.NavigationVariable-1478577159145",
    "name" : "goToPage_MyMunicipality",
    "owner" : "App",
    "category" : "wm.NavigationVariable",
    "dataBinding" : [ ],
    "operation" : "gotoPage",
    "pageName" : "MyMunicipality",
    "dataSet" : [ ],
    "pageTransitions" : "none"
  },
  "goToPage_MyProfile" : {
    "_id" : "wm-goToPage_MyProfile-wm.NavigationVariable-1478577295407",
    "name" : "goToPage_MyProfile",
    "owner" : "App",
    "category" : "wm.NavigationVariable",
    "dataBinding" : [ ],
    "operation" : "gotoPage",
    "pageName" : "MyProfile",
    "dataSet" : [ ],
    "pageTransitions" : "none"
  },
  "goToPage_MyProjects" : {
    "_id" : "wm-goToPage_MyProjects-wm.NavigationVariable-1486715945008",
    "name" : "goToPage_MyProjects",
    "owner" : "App",
    "category" : "wm.NavigationVariable",
    "dataBinding" : [ {
      "target" : "pageName",
      "value" : "MyProjects",
      "type" : "string"
    } ],
    "operation" : "gotoPage",
    "pageName" : "MyProjects",
    "dataSet" : [ {
      "type" : "integer",
      "target" : "municipalityId",
      "value" : "bind:!!Widgets.panelSelectMunicipality.Widgets.selectMunicipality.datavalue.ID ? Widgets.panelSelectMunicipality.Widgets.selectMunicipality.datavalue.ID : null"
    } ],
    "pageTransitions" : "none"
  },
  "goToPage_NewCases" : {
    "_id" : "wm-goToPage_NewCases-wm.NavigationVariable-1491476304176",
    "name" : "goToPage_NewCases",
    "owner" : "App",
    "category" : "wm.NavigationVariable",
    "dataBinding" : [ ],
    "operation" : "gotoPage",
    "pageName" : "NewCases",
    "dataSet" : [ ],
    "pageTransitions" : "none"
  },
  "goToPage_NewForm" : {
    "_id" : "wm-goToPage_NewForm-wm.NavigationVariable-1485785723881",
    "name" : "goToPage_NewForm",
    "owner" : "App",
    "category" : "wm.NavigationVariable",
    "dataBinding" : [ ],
    "operation" : "gotoPage",
    "pageName" : "NewForm",
    "dataSet" : [ ],
    "pageTransitions" : "none"
  },
  "goToPage_OpenCases" : {
    "_id" : "wm-goToPage_OpenCases-wm.NavigationVariable-1491395542156",
    "name" : "goToPage_OpenCases",
    "owner" : "App",
    "category" : "wm.NavigationVariable",
    "dataBinding" : [ ],
    "operation" : "gotoPage",
    "pageName" : "OpenCases",
    "dataSet" : [ ],
    "pageTransitions" : "none"
  },
  "goToPage_ProcessForms" : {
    "_id" : "wm-goToPage_ProcessForms-wm.NavigationVariable-1482317640483",
    "name" : "goToPage_ProcessForms",
    "owner" : "App",
    "category" : "wm.NavigationVariable",
    "dataBinding" : [ ],
    "operation" : "gotoPage",
    "pageName" : "ProcessForms",
    "dataSet" : [ ],
    "pageTransitions" : "none"
  },
  "goToPage_ProjectsDevDataEntry" : {
    "_id" : "wm-goToPage_ProjectsDevDataEntry-wm.NavigationVariable-1487157016005",
    "name" : "goToPage_ProjectsDevDataEntry",
    "owner" : "App",
    "category" : "wm.NavigationVariable",
    "dataBinding" : [ ],
    "operation" : "gotoPage",
    "pageName" : "ProjectsDevDataEntry",
    "dataSet" : [ ],
    "pageTransitions" : "none"
  },
  "goToPage_ResetPassword" : {
    "_id" : "wm-goToPage_ResetPassword-wm.NavigationVariable-1479884962543",
    "name" : "goToPage_ResetPassword",
    "owner" : "App",
    "category" : "wm.NavigationVariable",
    "dataBinding" : [ ],
    "operation" : "gotoPage",
    "pageName" : "ResetPassword",
    "dataSet" : [ ],
    "pageTransitions" : "none"
  },
  "goToPage_ScheduleInspections" : {
    "_id" : "wm-goToPage_ScheduleInspections-wm.NavigationVariable-1490948959704",
    "name" : "goToPage_ScheduleInspections",
    "owner" : "App",
    "category" : "wm.NavigationVariable",
    "dataBinding" : [ ],
    "operation" : "gotoPage",
    "pageName" : "ScheduleInspections",
    "dataSet" : [ ],
    "pageTransitions" : "none"
  },
  "goToPage_Support" : {
    "_id" : "wm-goToPage_Support-wm.NavigationVariable-1478577248530",
    "name" : "goToPage_Support",
    "owner" : "App",
    "category" : "wm.NavigationVariable",
    "dataBinding" : [ ],
    "operation" : "gotoPage",
    "pageName" : "Support",
    "dataSet" : [ ],
    "pageTransitions" : "none"
  },
  "goToPage_Test" : {
    "_id" : "wm-goToPage_Test-wm.NavigationVariable-1488178862265",
    "name" : "goToPage_Test",
    "owner" : "App",
    "category" : "wm.NavigationVariable",
    "dataBinding" : [ ],
    "operation" : "gotoPage",
    "pageName" : "Test",
    "dataSet" : [ ],
    "pageTransitions" : "none"
  },
  "goToPage_TodayInspections" : {
    "_id" : "wm-goToPage_TodayInspections-wm.NavigationVariable-1490933158107",
    "name" : "goToPage_TodayInspections",
    "owner" : "App",
    "category" : "wm.NavigationVariable",
    "dataBinding" : [ ],
    "operation" : "gotoPage",
    "pageName" : "TodayInspections",
    "dataSet" : [ ],
    "pageTransitions" : "none"
  },
  "goToPage_TomorrowInspections" : {
    "_id" : "wm-goToPage_TomorrowInspections-wm.NavigationVariable-1490961084570",
    "name" : "goToPage_TomorrowInspections",
    "owner" : "App",
    "category" : "wm.NavigationVariable",
    "dataBinding" : [ ],
    "operation" : "gotoPage",
    "pageName" : "TomorrowInspections",
    "dataSet" : [ ],
    "pageTransitions" : "none"
  },
  "goToPage_UserClosedForms" : {
    "_id" : "wm-goToPage_UserClosedForms-wm.NavigationVariable-1482831972576",
    "name" : "goToPage_UserClosedForms",
    "owner" : "App",
    "category" : "wm.NavigationVariable",
    "dataBinding" : [ {
      "target" : "pageName",
      "value" : "UserClosedForms",
      "type" : "string"
    } ],
    "operation" : "gotoPage",
    "pageName" : "UserClosedForms",
    "dataSet" : [ {
      "type" : "integer",
      "target" : "municipalityId",
      "value" : "bind:!!Widgets.panelSelectMunicipality.Widgets.selectMunicipality.datavalue.ID ? Widgets.panelSelectMunicipality.Widgets.selectMunicipality.datavalue.ID : null"
    } ],
    "pageTransitions" : "none"
  },
  "goToPage_UserCreation" : {
    "_id" : "wm-goToPage_UserCreation-wm.NavigationVariable-1478587383573",
    "name" : "goToPage_UserCreation",
    "owner" : "App",
    "category" : "wm.NavigationVariable",
    "dataBinding" : [ ],
    "operation" : "gotoPage",
    "pageName" : "UserCreation",
    "dataSet" : [ ],
    "pageTransitions" : "none"
  },
  "goToPage_UserOpenForms" : {
    "_id" : "wm-goToPage_UserOpenForms-wm.NavigationVariable-1482835065103",
    "name" : "goToPage_UserOpenForms",
    "owner" : "App",
    "category" : "wm.NavigationVariable",
    "dataBinding" : [ {
      "target" : "pageName",
      "value" : "UserOpenForms",
      "type" : "string"
    } ],
    "operation" : "gotoPage",
    "pageName" : "UserOpenForms",
    "dataSet" : [ {
      "type" : "integer",
      "target" : "municipalityId",
      "value" : "bind:!!Widgets.panelSelectMunicipality.Widgets.selectMunicipality.datavalue.ID ? Widgets.panelSelectMunicipality.Widgets.selectMunicipality.datavalue.ID : null"
    } ],
    "pageTransitions" : "none"
  },
  "goToPage_UserStatistics" : {
    "_id" : "wm-goToPage_UserStatistics-wm.NavigationVariable-1488198163131",
    "name" : "goToPage_UserStatistics",
    "owner" : "App",
    "category" : "wm.NavigationVariable",
    "dataBinding" : [ ],
    "operation" : "gotoPage",
    "pageName" : "UserStatistics",
    "dataSet" : [ ],
    "pageTransitions" : "none"
  },
  "goToPage_VendorApplication" : {
    "_id" : "wm-goToPage_VendorApplication-wm.NavigationVariable-1480415119127",
    "name" : "goToPage_VendorApplication",
    "owner" : "App",
    "category" : "wm.NavigationVariable",
    "dataBinding" : [ ],
    "operation" : "gotoPage",
    "pageName" : "VendorApplication",
    "dataSet" : [ ],
    "pageTransitions" : "none"
  },
  "goToPage_ViewCase" : {
    "_id" : "wm-goToPage_ViewCase-wm.NavigationVariable-1489486004689",
    "name" : "goToPage_ViewCase",
    "owner" : "App",
    "category" : "wm.NavigationVariable",
    "dataBinding" : [ ],
    "operation" : "gotoPage",
    "pageName" : "ViewCase",
    "dataSet" : [ ],
    "pageTransitions" : "none"
  },
  "goToPage_ViewInspection" : {
    "_id" : "wm-goToPage_ViewInspection-wm.NavigationVariable-1489488795493",
    "name" : "goToPage_ViewInspection",
    "owner" : "App",
    "category" : "wm.NavigationVariable",
    "dataBinding" : [ ],
    "operation" : "gotoPage",
    "pageName" : "ViewInspection",
    "dataSet" : [ ],
    "pageTransitions" : "none"
  },
  "goToPage_ViewProject" : {
    "_id" : "wm-goToPage_ViewProject-wm.NavigationVariable-1486718548788",
    "name" : "goToPage_ViewProject",
    "owner" : "App",
    "category" : "wm.NavigationVariable",
    "dataBinding" : [ ],
    "operation" : "gotoPage",
    "pageName" : "ViewProject",
    "dataSet" : [ ],
    "pageTransitions" : "none"
  },
  "goToPage_WorkSchedule" : {
    "_id" : "wm-goToPage_WorkSchedule-wm.NavigationVariable-1479370656242",
    "name" : "goToPage_WorkSchedule",
    "owner" : "App",
    "category" : "wm.NavigationVariable",
    "dataBinding" : [ ],
    "operation" : "gotoPage",
    "pageName" : "WorkSchedule",
    "dataSet" : [ ],
    "pageTransitions" : "none"
  },
  "goToPage_YesterdayInspections" : {
    "_id" : "wm-goToPage_YesterdayInspections-wm.NavigationVariable-1490961103232",
    "name" : "goToPage_YesterdayInspections",
    "owner" : "App",
    "category" : "wm.NavigationVariable",
    "dataBinding" : [ ],
    "operation" : "gotoPage",
    "pageName" : "YesterdayInspections",
    "dataSet" : [ ],
    "pageTransitions" : "none"
  },
  "loggedInUser" : {
    "_id" : "wm-loggedInUser-wm.Variable-1478578831248",
    "name" : "loggedInUser",
    "owner" : "App",
    "category" : "wm.Variable",
    "dataBinding" : [ ],
    "dataSet" : {
      "name" : "",
      "id" : "",
      "tenantId" : "",
      "isAuthenticated" : false,
      "isSecurityEnabled" : true,
      "roles" : [ ]
    },
    "type" : "string",
    "isList" : false,
    "saveInPhonegap" : false
  },
  "LoginFailed" : {
    "_id" : "wm-LoginFailed-wm.NotificationVariable-1484028249735",
    "name" : "LoginFailed",
    "owner" : "App",
    "category" : "wm.NotificationVariable",
    "dataBinding" : [ {
      "target" : "content",
      "value" : "inline",
      "type" : "string"
    }, {
      "target" : "text",
      "value" : "Your password is incorrect. Please check your password and try again.",
      "type" : "string"
    }, {
      "target" : "duration",
      "value" : "2000",
      "type" : "number"
    }, {
      "target" : "class",
      "value" : "Error",
      "type" : "string"
    }, {
      "target" : "toasterPosition",
      "value" : "bottom right",
      "type" : "string"
    } ],
    "operation" : "toast"
  },
  "loginVariable" : {
    "_id" : "wm-loginVariable-wm.LoginVariable-1478578831247",
    "name" : "loginVariable",
    "owner" : "App",
    "category" : "wm.LoginVariable",
    "dataBinding" : [ {
      "target" : "username",
      "value" : "bind:Widgets.usernametext.datavalue",
      "type" : "string"
    }, {
      "target" : "password",
      "value" : "bind:Widgets.passwordtext.datavalue",
      "type" : "string"
    }, {
      "target" : "rememberme",
      "value" : "bind:Widgets.remembermecheck.datavalue",
      "type" : "boolean"
    } ],
    "dataSet" : {
      "username" : "",
      "password" : "",
      "rememberme" : false
    },
    "type" : "string",
    "saveInPhonegap" : false,
    "onError" : "Variables.LoginFailed.invoke()",
    "startUpdate" : false,
    "autoUpdate" : false,
    "inFlightBehavior" : "executeLast",
    "transformationRequired" : false,
    "useDefaultSuccessHandler" : true
  },
  "logoutVariable" : {
    "_id" : "wm-logoutVariable-wm.LogoutVariable-1478578831247",
    "name" : "logoutVariable",
    "owner" : "App",
    "category" : "wm.LogoutVariable",
    "type" : "string",
    "saveInPhonegap" : false,
    "onSuccess" : "Variables.ResetPaswordSuccess.invoke()",
    "inFlightBehavior" : "executeLast",
    "transformationRequired" : false,
    "redirectTo" : "Login",
    "useDefaultSuccessHandler" : true
  },
  "MCNewElectricConnection" : {
    "_id" : "wm-goToPage_MCNewElectricConnection-wm.NavigationVariable-1481013591760",
    "name" : "MCNewElectricConnection",
    "owner" : "App",
    "category" : "wm.NavigationVariable",
    "dataBinding" : [ {
      "target" : "pageName",
      "value" : "MCNewElectricConnection",
      "type" : "list"
    } ],
    "operation" : "gotoPage",
    "pageName" : "MCNewElectricConnection",
    "dataSet" : [ ],
    "pageTransitions" : "none"
  },
  "MCNewResidentialStructure" : {
    "_id" : "wm-goToPage_MCNewResidentialStructure-wm.NavigationVariable-1481017443320",
    "name" : "MCNewResidentialStructure",
    "owner" : "App",
    "category" : "wm.NavigationVariable",
    "dataBinding" : [ {
      "target" : "pageName",
      "value" : "MCNewResidentialStructure",
      "type" : "list"
    } ],
    "operation" : "gotoPage",
    "pageName" : "MCNewResidentialStructure",
    "dataSet" : [ ],
    "pageTransitions" : "none"
  },
  "MyCompaniesCount" : {
    "_id" : "wm-MyCompaniesCount-wm.Variable-1480937483790",
    "name" : "MyCompaniesCount",
    "owner" : "App",
    "category" : "wm.Variable",
    "dataBinding" : [ ],
    "dataSet" : {
      "dataValue" : ""
    },
    "type" : "string",
    "isList" : false,
    "saveInPhonegap" : false
  },
  "NewUserToLogin" : {
    "_id" : "wm-NewUserToLogin-wm.NavigationVariable-1478606207596",
    "name" : "NewUserToLogin",
    "owner" : "App",
    "category" : "wm.NavigationVariable",
    "dataBinding" : [ {
      "target" : "pageName",
      "value" : "Login",
      "type" : "list"
    } ],
    "operation" : "gotoPage",
    "dataSet" : [ ],
    "pageTransitions" : "none"
  },
  "NoOfMunicipalitiesForUser" : {
    "_id" : "wm-NoOfMunicipalitiesForUser-wm.Variable-1478779818280",
    "name" : "NoOfMunicipalitiesForUser",
    "owner" : "App",
    "category" : "wm.Variable",
    "dataBinding" : [ ],
    "dataSet" : {
      "dataValue" : 0
    },
    "type" : "number",
    "isList" : false,
    "saveInPhonegap" : false
  },
  "ProcessFormsCountForEmployee" : {
    "_id" : "wm-ProcessFormsCountForEmployee-wm.Variable-1486466579855",
    "name" : "ProcessFormsCountForEmployee",
    "owner" : "App",
    "category" : "wm.Variable",
    "dataBinding" : [ ],
    "dataSet" : {
      "dataValue" : ""
    },
    "type" : "string",
    "isList" : false,
    "saveInPhonegap" : false
  },
  "ProjectCreatedSuccesfully" : {
    "_id" : "wm-ProjectCreatedSuccesfully-wm.NotificationVariable-1488783338225",
    "name" : "ProjectCreatedSuccesfully",
    "owner" : "App",
    "category" : "wm.NotificationVariable",
    "dataBinding" : [ {
      "target" : "content",
      "value" : "inline",
      "type" : "string"
    }, {
      "target" : "text",
      "value" : "Your project has been created successfully",
      "type" : "string"
    }, {
      "target" : "duration",
      "value" : "5000",
      "type" : "number"
    }, {
      "target" : "class",
      "value" : "Success",
      "type" : "string"
    }, {
      "target" : "toasterPosition",
      "value" : "bottom right",
      "type" : "string"
    } ],
    "operation" : "toast"
  },
  "PUDApplication" : {
    "_id" : "wm-goToPage_PUDApplication-wm.NavigationVariable-1481015708845",
    "name" : "PUDApplication",
    "owner" : "App",
    "category" : "wm.NavigationVariable",
    "dataBinding" : [ {
      "target" : "pageName",
      "value" : "PUDApplication",
      "type" : "list"
    } ],
    "operation" : "gotoPage",
    "pageName" : "PUDApplication",
    "dataSet" : [ ],
    "pageTransitions" : "none"
  },
  "ResetPaswordSuccess" : {
    "_id" : "wm-ResetPaswordSuccess-wm.NotificationVariable-1486358204737",
    "name" : "ResetPaswordSuccess",
    "owner" : "App",
    "category" : "wm.NotificationVariable",
    "dataBinding" : [ {
      "target" : "content",
      "value" : "inline",
      "type" : "string"
    }, {
      "target" : "text",
      "value" : "Your new password has been set. Please proceed to Login",
      "type" : "string"
    }, {
      "target" : "duration",
      "value" : "5000",
      "type" : "number"
    }, {
      "target" : "class",
      "value" : "Success",
      "type" : "string"
    }, {
      "target" : "toasterPosition",
      "value" : "bottom right",
      "type" : "string"
    } ],
    "operation" : "toast"
  },
  "SFNewElectricConnection" : {
    "_id" : "wm-goToPage_SFNewElectricConnection-wm.NavigationVariable-1479304018405",
    "name" : "SFNewElectricConnection",
    "owner" : "App",
    "category" : "wm.NavigationVariable",
    "dataBinding" : [ {
      "target" : "pageName",
      "value" : "SFNewElectricConnection",
      "type" : "list"
    } ],
    "operation" : "gotoPage",
    "pageName" : "SFNewElectricConnection",
    "dataSet" : [ ],
    "pageTransitions" : "none"
  },
  "SFNewResidentialStructure" : {
    "_id" : "wm-goToPage_SFNewResidentialStructure-wm.NavigationVariable-1479115891779",
    "name" : "SFNewResidentialStructure",
    "owner" : "App",
    "category" : "wm.NavigationVariable",
    "dataBinding" : [ {
      "target" : "pageName",
      "value" : "SFNewResidentialStructure",
      "type" : "list"
    } ],
    "operation" : "gotoPage",
    "pageName" : "SFNewResidentialStructure",
    "dataSet" : [ ],
    "pageTransitions" : "none"
  },
  "StandardUserMunicipalities" : {
    "_id" : "wm-StandardUserMunicipalites-wm.ServiceVariable-1478775230336",
    "name" : "StandardUserMunicipalities",
    "owner" : "App",
    "category" : "wm.ServiceVariable",
    "dataBinding" : [ {
      "target" : "USER",
      "value" : "bind:Variables.CurrentUserDetails.dataSet.id",
      "type" : "integer"
    } ],
    "type" : "com.civicxpress.cx2.models.query.StandardUserMunicipalitesResponse",
    "service" : "cx2",
    "operation" : "executeStandardUserMunicipalites",
    "operationId" : "QueryExecutionController_executeStandardUserMunicipalites",
    "operationType" : "get",
    "serviceType" : "DataService",
    "dataSet" : [ ],
    "isList" : true,
    "maxResults" : 20,
    "designMaxResults" : 10,
    "onSuccess" : "StandardUserMunicipalitesonSuccess($event, $scope)",
    "startUpdate" : false,
    "autoUpdate" : true,
    "inFlightBehavior" : "executeLast",
    "transformationRequired" : false,
    "saveInPhonegap" : false,
    "controller" : "QueryExecution"
  },
  "stvCartCount" : {
    "_id" : "wm-stvCartCount-wm.Variable-1490685757724",
    "name" : "stvCartCount",
    "owner" : "App",
    "category" : "wm.Variable",
    "dataBinding" : [ ],
    "dataSet" : {
      "dataValue" : ""
    },
    "type" : "string",
    "isList" : false,
    "saveInPhonegap" : false
  },
  "successfully" : {
    "_id" : "wm-successfully-wm.NotificationVariable-1481869693445",
    "name" : "successfully",
    "owner" : "App",
    "category" : "wm.NotificationVariable",
    "dataBinding" : [ {
      "target" : "content",
      "value" : "inline",
      "type" : "list"
    }, {
      "target" : "text",
      "value" : "Record Added successfully",
      "type" : "string"
    }, {
      "target" : "duration",
      "value" : "5000",
      "type" : "list"
    }, {
      "target" : "class",
      "value" : "Success",
      "type" : "list"
    }, {
      "target" : "toasterPosition",
      "value" : "bottom right",
      "type" : "list"
    } ],
    "operation" : "toast"
  },
  "supportedLocale" : {
    "_id" : "wm-wm.Variable1402640443182",
    "name" : "supportedLocale",
    "owner" : "App",
    "category" : "wm.Variable",
    "dataSet" : {
      "en" : "English"
    },
    "type" : "string",
    "isList" : false,
    "saveInPhonegap" : false
  },
  "svCartItemIds" : {
    "_id" : "wm-svCartItemIds-wm.ServiceVariable-1490685014948",
    "name" : "svCartItemIds",
    "owner" : "App",
    "category" : "wm.ServiceVariable",
    "dataBinding" : [ {
      "target" : "userId",
      "value" : "bind:Variables.loggedInUser.dataSet.id",
      "type" : "integer"
    } ],
    "type" : "com.civicxpress.cx2.models.query.GetCartItemIdsResponse",
    "service" : "cx2",
    "operation" : "executeGetCartItemIds",
    "operationId" : "QueryExecutionController_executeGetCartItemIds",
    "operationType" : "get",
    "serviceType" : "DataService",
    "dataSet" : [ ],
    "isList" : true,
    "maxResults" : 9000,
    "designMaxResults" : 10,
    "onSuccess" : "svCartItemIdsonSuccess($event, $scope)",
    "startUpdate" : false,
    "autoUpdate" : true,
    "inFlightBehavior" : "executeLast",
    "transformationRequired" : false,
    "saveInPhonegap" : false,
    "controller" : "QueryExecution"
  },
  "UserOpenFormsCount" : {
    "_id" : "wm-UserOpenFormsCount-wm.Variable-1486466257530",
    "name" : "UserOpenFormsCount",
    "owner" : "App",
    "category" : "wm.Variable",
    "dataBinding" : [ ],
    "dataSet" : {
      "dataValue" : ""
    },
    "type" : "string",
    "isList" : false,
    "saveInPhonegap" : false
  }
}